yo.py
yo_runner-0.1.2.dist-info/entry_points.txt
yo_runner-0.1.2.dist-info/WHEEL
yo_runner-0.1.2.dist-info/METADATA
yo_runner-0.1.2.dist-info/RECORD
