Metadata-Version: 2.1
Name: yo-runner
Version: 0.1.2
Summary: A YAML-driven task runner for lazy people
Home-page: https://github.com/OliverSherouse/yo-runner
License: GPL-2.0+
Keywords: build,task,runner
Author: Oliver Sherouse
Author-email: oliver@oliversherouse.com
Requires-Python: >=3.6
Classifier: Development Status :: 4 - Beta
Classifier: Intended Audience :: Developers
Classifier: License :: OSI Approved :: GNU General Public License v2 or later (GPLv2+)
Classifier: License :: OSI Approved :: MIT License
Classifier: Operating System :: OS Independent
Classifier: Programming Language :: Python :: 3
Classifier: Programming Language :: Python :: 3.6
Classifier: Programming Language :: Python :: 3.7
Classifier: Topic :: Software Development :: Build Tools
Classifier: Topic :: Utilities
Requires-Dist: pyyaml (>=3.13)
Project-URL: Repository, https://github.com/OliverSherouse/yo-runner
